build_filesystem_trie.py
build_filesystem_trie-0.1.0a6.dist-info/licenses/LICENSE
build_filesystem_trie-0.1.0a6.dist-info/METADATA
build_filesystem_trie-0.1.0a6.dist-info/WHEEL
build_filesystem_trie-0.1.0a6.dist-info/top_level.txt
build_filesystem_trie-0.1.0a6.dist-info/RECORD
