Metadata-Version: 2.4
Name: build-filesystem-trie
Version: 0.1.0a6
Summary: Programmatically generate a trie representing a section of the filesystem, closely matching what the UNIX `tree` command outputs.
Author-email: Jifeng Wu <jifengwu2k@gmail.com>
License-Expression: MIT
Project-URL: Homepage, https://github.com/jifengwu2k/build-filesystem-trie
Project-URL: Bug Tracker, https://github.com/jifengwu2k/build-filesystem-trie/issues
Classifier: Programming Language :: Python :: 2
Classifier: Programming Language :: Python :: 3
Classifier: Operating System :: OS Independent
Requires-Python: >=2
License-File: LICENSE
Requires-Dist: cowlist
Requires-Dist: fspathverbs
Requires-Dist: tinytrie
Requires-Dist: typing; python_version < "3.5"
Dynamic: license-file
